{
  "version": 2,
  "generator": "@async/pipeline",
  "config": "pipeline.ts",
  "workflow": ".github/workflows/async-pipeline.yml",
  "hash": "sha256:e82593e9dca25655c00777397a1f2a0ff7dcb7788595e42348236ef21a08fc41",
  "generatedAt": "2026-06-14T06:26:19.615Z",
  "triggers": {
    "pull_request": {},
    "push": {
      "branches": [
        "main"
      ]
    },
    "workflow_dispatch": {}
  },
  "jobs": [
    {
      "id": "verifyImpact",
      "target": [
        "impact"
      ],
      "trigger": [
        "pr",
        "main",
        "manual"
      ],
      "env": {},
      "if": "(github.event_name == 'pull_request') || (github.event_name == 'push' && (github.ref == 'refs/heads/main')) || (github.event_name == 'workflow_dispatch' && github.event.inputs.job == 'verifyImpact')"
    }
  ],
  "packageManager": "pnpm",
  "nodeVersion": "24",
  "taskCache": true,
  "manualDispatchJobs": [
    "verifyImpact"
  ]
}
